otx/__init__.py
otx/backend/__init__.py
otx/backend/native/__init__.py
otx/backend/native/engine.py
otx/backend/native/callbacks/__init__.py
otx/backend/native/callbacks/adaptive_early_stopping.py
otx/backend/native/callbacks/adaptive_train_scheduling.py
otx/backend/native/callbacks/aug_scheduler.py
otx/backend/native/callbacks/batchsize_finder.py
otx/backend/native/callbacks/gpu_mem_monitor.py
otx/backend/native/callbacks/iteration_timer.py
otx/backend/native/cli/__init__.py
otx/backend/native/cli/utils.py
otx/backend/native/exporter/__init__.py
otx/backend/native/exporter/anomaly.py
otx/backend/native/exporter/base.py
otx/backend/native/exporter/native.py
otx/backend/native/exporter/exportable_code/__init__.py
otx/backend/native/exporter/exportable_code/demo/LICENSE
otx/backend/native/exporter/exportable_code/demo/README.md
otx/backend/native/exporter/exportable_code/demo/__init__.py
otx/backend/native/exporter/exportable_code/demo/demo.py
otx/backend/native/exporter/exportable_code/demo/requirements.txt
otx/backend/native/exporter/exportable_code/demo/setup.py
otx/backend/native/exporter/exportable_code/demo/demo_package/__init__.py
otx/backend/native/exporter/exportable_code/demo/demo_package/model_wrapper.py
otx/backend/native/exporter/exportable_code/demo/demo_package/utils.py
otx/backend/native/exporter/exportable_code/demo/demo_package/executors/__init__.py
otx/backend/native/exporter/exportable_code/demo/demo_package/executors/asynchronous.py
otx/backend/native/exporter/exportable_code/demo/demo_package/executors/synchronous.py
otx/backend/native/exporter/exportable_code/demo/demo_package/streamer/__init__.py
otx/backend/native/exporter/exportable_code/demo/demo_package/streamer/streamer.py
otx/backend/native/exporter/exportable_code/demo/demo_package/visualizers/__init__.py
otx/backend/native/exporter/exportable_code/demo/demo_package/visualizers/vis_utils.py
otx/backend/native/exporter/exportable_code/demo/demo_package/visualizers/visualizer.py
otx-2.6.0.dist-info/METADATA
otx-2.6.0.dist-info/WHEEL
otx-2.6.0.dist-info/entry_points.txt
otx-2.6.0.dist-info/top_level.txt
otx-2.6.0.dist-info/RECORD
